bootstrapsidebar/__init__.py
bootstrapsidebar/apps.py
bootstrapsidebar/tests.py
bootstrapsidebar/static/bootstrapsidebar-fonts.min.css
bootstrapsidebar/static/bootstrapsidebar-fonts.min.css.map
bootstrapsidebar/static/layout.css
bootstrapsidebar/static/bootstrap/.gitignore
bootstrapsidebar/static/bootstrap/bootstrap.bundle.min.js
bootstrapsidebar/static/bootstrap/bootstrap.bundle.min.js.map
bootstrapsidebar/static/bootstrap/sidebar-bootstrap.min.css
bootstrapsidebar/static/bootstrap/sidebar-bootstrap.min.css.map
bootstrapsidebar/static/fonts/.gitignore
bootstrapsidebar/static/fonts/JTUSjIg1_i6t8kCHKm459W1hyzbi.woff2
bootstrapsidebar/static/fonts/JTUSjIg1_i6t8kCHKm459WRhyzbi.woff2
bootstrapsidebar/static/fonts/JTUSjIg1_i6t8kCHKm459WZhyzbi.woff2
bootstrapsidebar/static/fonts/JTUSjIg1_i6t8kCHKm459Wdhyzbi.woff2
bootstrapsidebar/static/fonts/JTUSjIg1_i6t8kCHKm459Wlhyw.woff2
bootstrapsidebar/static/img/cc-logo.svg
bootstrapsidebar/static/mdi/menu.svg
bootstrapsidebar/templates/403.html
bootstrapsidebar/templates/404.html
bootstrapsidebar/templates/500.html
bootstrapsidebar/templates/bootstrap_base.html
bootstrapsidebar/templates/registration/login.html
bootstrapsidebar/templates/registration/password_change_form.html
bootstrapsidebar/templates/snippets/show_err.html
bootstrapsidebar/templates/snippets/show_messages.html
django_bootstrap_sidebar-1.2.8.dist-info/licenses/LICENSE
django_bootstrap_sidebar-1.2.8.dist-info/METADATA
django_bootstrap_sidebar-1.2.8.dist-info/WHEEL
django_bootstrap_sidebar-1.2.8.dist-info/top_level.txt
django_bootstrap_sidebar-1.2.8.dist-info/RECORD
