Metadata-Version: 2.4
Name: django-bootstrap-sidebar
Version: 1.2.8
Summary: Bootstrap 5.3 template for Django 5 and 6
Home-page: https://github.com/paulino/django-bootstrap-sidebar
Author: Paulino Ruiz de Clavijo Vázquez
Author-email: pruiz@us.esS
License: Apache-2.0
Project-URL: Bug Tracker, https://github.com/paulino/django-bootstrap-sidebar/issues
Project-URL: GitHub, https://github.com/paulino/django-bootstrap-sidebar/
Project-URL: Changelog, https://github.com/paulino/django-bootstrap-sidebar/blob/master/CHANGELOG.md
Classifier: Programming Language :: Python :: 3
Classifier: License :: OSI Approved :: Apache Software License
Classifier: Operating System :: OS Independent
Requires-Python: >=3.6
License-File: LICENSE
Dynamic: license-file
